{"temp":{"en":{"data":[{"name":"maximum temperature","data":[19,19,21,19,19,19,20,22,21]},{"name":"minimum temperature","data":[14,13,14,13,14,14,15,17,16]}],"categories":[["19 Dec","(Thu)"],["20 Dec","(Fri)"],["21 Dec","(Sat)"],["22 Dec","(Sun)"],["23 Dec","(Mon)"],["24 Dec","(Tue)"],["25 Dec","(Wed)"],["26 Dec","(Thu)"],["27 Dec","(Fri)"]],"title":"Temperature (°C)"},"tc":{"data":[{"name":"最高温度","data":[19,19,21,19,19,19,20,22,21]},{"name":"最低温度","data":[14,13,14,13,14,14,15,17,16]}],"categories":[["12月19日","(星期四)"],["12月20日","(星期五)"],["12月21日","(星期六)"],["12月22日","(星期日)"],["12月23日","(星期一)"],["12月24日","(星期二)"],["12月25日","(星期三)"],["12月26日","(星期四)"],["12月27日","(星期五)"]],"title":"溫度 (°C)"},"sc":{"data":[{"name":"最高溫度","data":[19,19,21,19,19,19,20,22,21]},{"name":" 最低溫度","data":[14,13,14,13,14,14,15,17,16]}],"categories":[["20241219","(星期四)"],["20241220","(星期五)"],["20241221","(星期六)"],["20241222","(星期日)"],["20241223","(星期一)"],["20241224","(星期二)"],["20241225","(星期三)"],["20241226","(星期四)"],["20241227","(星期五)"]],"title":"温度 (°C)"}},"hum":{"en":{"data":[{"name":"最高相对湿度","data":[60,60,65,65,75,75,80,75,80]},{"name":"最低相对湿度","data":[35,35,30,35,40,45,50,50,55]}],"categories":[["20241219","(星期四)"],["20241220","(星期五)"],["20241221","(星期六)"],["20241222","(星期日)"],["20241223","(星期一)"],["20241224","(星期二)"],["20241225","(星期三)"],["20241226","(星期四)"],["20241227","(星期五)"]],"title":"相对湿度 (%)"},"tc":{"data":[{"name":"最高相对湿度","data":[60,60,65,65,75,75,80,75,80]},{"name":"最低相对湿度","data":[35,35,30,35,40,45,50,50,55]}],"categories":[["20241219","(星期四)"],["20241220","(星期五)"],["20241221","(星期六)"],["20241222","(星期日)"],["20241223","(星期一)"],["20241224","(星期二)"],["20241225","(星期三)"],["20241226","(星期四)"],["20241227","(星期五)"]],"title":"相对湿度 (%)"},"sc":{"data":[{"name":"最高相对湿度","data":[60,60,65,65,75,75,80,75,80]},{"name":"最低相对湿度","data":[35,35,30,35,40,45,50,50,55]}],"categories":[["20241219","(星期四)"],["20241220","(星期五)"],["20241221","(星期六)"],["20241222","(星期日)"],["20241223","(星期一)"],["20241224","(星期二)"],["20241225","(星期三)"],["20241226","(星期四)"],["20241227","(星期五)"]],"title":"相对湿度 (%)"}}}