{"temp":{"en":{"data":[{"name":"maximum temperature","data":[30,31,30,30,30,32,33,33,33]},{"name":"minimum temperature","data":[26,27,26,26,26,27,28,28,28]}],"categories":[["17 Aug","(Sat)"],["18 Aug","(Sun)"],["19 Aug","(Mon)"],["20 Aug","(Tue)"],["21 Aug","(Wed)"],["22 Aug","(Thu)"],["23 Aug","(Fri)"],["24 Aug","(Sat)"],["25 Aug","(Sun)"]],"title":"Temperature (°C)"},"tc":{"data":[{"name":"最高温度","data":[30,31,30,30,30,32,33,33,33]},{"name":"最低温度","data":[26,27,26,26,26,27,28,28,28]}],"categories":[["8月17日","(星期六)"],["8月18日","(星期日)"],["8月19日","(星期一)"],["8月20日","(星期二)"],["8月21日","(星期三)"],["8月22日","(星期四)"],["8月23日","(星期五)"],["8月24日","(星期六)"],["8月25日","(星期日)"]],"title":"溫度 (°C)"},"sc":{"data":[{"name":"最高溫度","data":[30,31,30,30,30,32,33,33,33]},{"name":" 最低溫度","data":[26,27,26,26,26,27,28,28,28]}],"categories":[["20240817","(星期六)"],["20240818","(星期日)"],["20240819","(星期一)"],["20240820","(星期二)"],["20240821","(星期三)"],["20240822","(星期四)"],["20240823","(星期五)"],["20240824","(星期六)"],["20240825","(星期日)"]],"title":"温度 (°C)"}},"hum":{"en":{"data":[{"name":"最高相对湿度","data":[95,95,95,95,95,90,90,90,90]},{"name":"最低相对湿度","data":[75,75,75,75,75,70,65,65,65]}],"categories":[["20240817","(星期六)"],["20240818","(星期日)"],["20240819","(星期一)"],["20240820","(星期二)"],["20240821","(星期三)"],["20240822","(星期四)"],["20240823","(星期五)"],["20240824","(星期六)"],["20240825","(星期日)"]],"title":"相对湿度 (%)"},"tc":{"data":[{"name":"最高相对湿度","data":[95,95,95,95,95,90,90,90,90]},{"name":"最低相对湿度","data":[75,75,75,75,75,70,65,65,65]}],"categories":[["20240817","(星期六)"],["20240818","(星期日)"],["20240819","(星期一)"],["20240820","(星期二)"],["20240821","(星期三)"],["20240822","(星期四)"],["20240823","(星期五)"],["20240824","(星期六)"],["20240825","(星期日)"]],"title":"相对湿度 (%)"},"sc":{"data":[{"name":"最高相对湿度","data":[95,95,95,95,95,90,90,90,90]},{"name":"最低相对湿度","data":[75,75,75,75,75,70,65,65,65]}],"categories":[["20240817","(星期六)"],["20240818","(星期日)"],["20240819","(星期一)"],["20240820","(星期二)"],["20240821","(星期三)"],["20240822","(星期四)"],["20240823","(星期五)"],["20240824","(星期六)"],["20240825","(星期日)"]],"title":"相对湿度 (%)"}}}