{"temp":{"en":{"data":[{"name":"maximum temperature","data":[34,33,33,32,30,30,31,32,32]},{"name":"minimum temperature","data":[28,28,28,27,27,27,27,28,28]}],"categories":[["06 Jul","(Sun)"],["07 Jul","(Mon)"],["08 Jul","(Tue)"],["09 Jul","(Wed)"],["10 Jul","(Thu)"],["11 Jul","(Fri)"],["12 Jul","(Sat)"],["13 Jul","(Sun)"],["14 Jul","(Mon)"]],"title":"Temperature (°C)"},"tc":{"data":[{"name":"最高温度","data":[34,33,33,32,30,30,31,32,32]},{"name":"最低温度","data":[28,28,28,27,27,27,27,28,28]}],"categories":[["7月6日","(星期日)"],["7月7日","(星期一)"],["7月8日","(星期二)"],["7月9日","(星期三)"],["7月10日","(星期四)"],["7月11日","(星期五)"],["7月12日","(星期六)"],["7月13日","(星期日)"],["7月14日","(星期一)"]],"title":"溫度 (°C)"},"sc":{"data":[{"name":"最高溫度","data":[34,33,33,32,30,30,31,32,32]},{"name":" 最低溫度","data":[28,28,28,27,27,27,27,28,28]}],"categories":[["20250706","(星期日)"],["20250707","(星期一)"],["20250708","(星期二)"],["20250709","(星期三)"],["20250710","(星期四)"],["20250711","(星期五)"],["20250712","(星期六)"],["20250713","(星期日)"],["20250714","(星期一)"]],"title":"温度 (°C)"}},"hum":{"en":{"data":[{"name":"最高相对湿度","data":[95,95,95,95,95,95,95,95,90]},{"name":"最低相对湿度","data":[55,65,65,70,80,80,75,70,70]}],"categories":[["20250706","(星期日)"],["20250707","(星期一)"],["20250708","(星期二)"],["20250709","(星期三)"],["20250710","(星期四)"],["20250711","(星期五)"],["20250712","(星期六)"],["20250713","(星期日)"],["20250714","(星期一)"]],"title":"相对湿度 (%)"},"tc":{"data":[{"name":"最高相对湿度","data":[95,95,95,95,95,95,95,95,90]},{"name":"最低相对湿度","data":[55,65,65,70,80,80,75,70,70]}],"categories":[["20250706","(星期日)"],["20250707","(星期一)"],["20250708","(星期二)"],["20250709","(星期三)"],["20250710","(星期四)"],["20250711","(星期五)"],["20250712","(星期六)"],["20250713","(星期日)"],["20250714","(星期一)"]],"title":"相对湿度 (%)"},"sc":{"data":[{"name":"最高相对湿度","data":[95,95,95,95,95,95,95,95,90]},{"name":"最低相对湿度","data":[55,65,65,70,80,80,75,70,70]}],"categories":[["20250706","(星期日)"],["20250707","(星期一)"],["20250708","(星期二)"],["20250709","(星期三)"],["20250710","(星期四)"],["20250711","(星期五)"],["20250712","(星期六)"],["20250713","(星期日)"],["20250714","(星期一)"]],"title":"相对湿度 (%)"}}}